LICENSE
README.md
pyproject.toml
setup.py
wise_pizza/__init__.py
wise_pizza/cluster.py
wise_pizza/dataframe_with_metadata.py
wise_pizza/explain.py
wise_pizza/make_matrix.py
wise_pizza/plotting.py
wise_pizza/plotting_time.py
wise_pizza/plotting_time_tree.py
wise_pizza/preselect.py
wise_pizza/run_streamlit_app_entry_point.py
wise_pizza/segment_data.py
wise_pizza/slicer.py
wise_pizza/slicer_facades.py
wise_pizza/slicer_plotting.py
wise_pizza/streamlit_app.py
wise_pizza/time.py
wise_pizza/transform.py
wise_pizza/utils.py
wise_pizza.egg-info/PKG-INFO
wise_pizza.egg-info/SOURCES.txt
wise_pizza.egg-info/dependency_links.txt
wise_pizza.egg-info/entry_points.txt
wise_pizza.egg-info/requires.txt
wise_pizza.egg-info/top_level.txt
wise_pizza/solve/__init__.py
wise_pizza/solve/find_alpha.py
wise_pizza/solve/fitter.py
wise_pizza/solve/partition.py
wise_pizza/solve/solver.py
wise_pizza/solve/tree.py
wise_pizza/solve/weighted_quantiles.py