Metadata-Version: 2.1
Name: wise-pizza
Version: 0.2.9
Summary: A library to find and visualise the most interesting slices in multidimensional data
Home-page: https://github.com/transferwise/wise-pizza
Author: Wise
Keywords: wise-pizza
Classifier: Programming Language :: Python :: 3 :: Only
Classifier: Programming Language :: Python :: 3.7
Classifier: Programming Language :: Python :: 3.8
Classifier: Programming Language :: Python :: 3.9
Provides-Extra: test
License-File: LICENSE
